odoo/addons/hr_expense_analytic_tag/README.rst
odoo/addons/hr_expense_analytic_tag/__init__.py
odoo/addons/hr_expense_analytic_tag/__manifest__.py
odoo/addons/hr_expense_analytic_tag/i18n/de.po
odoo/addons/hr_expense_analytic_tag/i18n/es.po
odoo/addons/hr_expense_analytic_tag/i18n/hr_expense_analytic_tag.pot
odoo/addons/hr_expense_analytic_tag/models/__init__.py
odoo/addons/hr_expense_analytic_tag/models/hr_expense.py
odoo/addons/hr_expense_analytic_tag/readme/CONTRIBUTORS.rst
odoo/addons/hr_expense_analytic_tag/readme/DESCRIPTION.rst
odoo/addons/hr_expense_analytic_tag/readme/USAGE.rst
odoo/addons/hr_expense_analytic_tag/static/description/icon.png
odoo/addons/hr_expense_analytic_tag/static/description/index.html
odoo/addons/hr_expense_analytic_tag/tests/__init__.py
odoo/addons/hr_expense_analytic_tag/tests/test_hr_expense_analytic_tag.py
odoo/addons/hr_expense_analytic_tag/views/hr_expense_sheet_views.xml
odoo/addons/hr_expense_analytic_tag/views/hr_expense_views.xml
odoo11_addon_hr_expense_analytic_tag-11.0.1.0.0.99.dev7.dist-info/METADATA
odoo11_addon_hr_expense_analytic_tag-11.0.1.0.0.99.dev7.dist-info/WHEEL
odoo11_addon_hr_expense_analytic_tag-11.0.1.0.0.99.dev7.dist-info/top_level.txt
odoo11_addon_hr_expense_analytic_tag-11.0.1.0.0.99.dev7.dist-info/RECORD
